Workbook

Sheet 195 States
A1: Country | B1: Head of state | C1: Head of government | D1: Ideological family | E1: Variant code | F1: Variant | G1: Secondary family | H1: Full code | I1: Decontested form (this government) | J1: Thin-centred components | K1: Adjacent concepts / regime context | L1: Policy approach / key domains | M1: Previous code (conservatism-only scheme)
A2: Afghanistan | B2: Hibatullah Akhundzada | C2: Hasan Akhund | D2: Religious-political ideology | E2: RE | F2: Theocracy | H2: RE | I2: Islamist theocracy (Taliban emirate) | K2: Authoritarian rule | L2: Tradition/religion; sharia; authority/order; restrictive social policy; state-controlled economy; restrictive migration; security-first foreign policy | M2: T — traditionalist-authoritarian
A3: Albania | B3: Bajram Begaj | C3: Edi Rama | D3: Socialism | E3: S | F3: Social democracy | G3: Liberalism | H3: S/LIB | I3: Third Way social democracy (Socialist Party) | L3: EU integration; social-democratic governance; market economy; gradual institutional reform; pragmatic migration policy | M3: L/C — centre-left
A4: Algeria | B4: Abdelmadjid Tebboune | C4: Sifi Ghrieb | D4: Socialism | E4: S+ | F4: Left-nationalist / left-populist socialism | H4: S+ | I4: Post-revolutionary state socialism and nationalism (FLN legacy) | J4: Nationalism | K4: Authoritarian rule | L4: National sovereignty; state role in economy; social conservatism; controlled migration; hydrocarbons; security/state continuity | M4: T — nationalist-authoritarian
A5: Andorra | B5: Josep-Lluís Serrano / Emmanuel Macron | C5: Xavier Espot | D5: Conservatism | E5: C | F5: Conservatism | G5: Liberalism | H5: C/LIB | I5: Liberal conservatism / Christian democracy | L5: Small-state market economy; institutional continuity; Catholic heritage; open European orientation | M5: C/L — liberal-conservative hybrid
A6: Angola | B6: João Lourenço | C6: João Lourenço | D6: Traditionalist-authoritarian | E6: T | F6: Traditionalist-authoritarian | G6: Socialism | H6: T/SOC | I6: Post-Marxist dominant-party developmentalism (MPLA) | J6: Nationalism | K6: Authoritarian rule; Developmentalism | L6: State authority; national development; market reform with state role; social conservatism; energy/resources; security | M6: C+/T — nationalist-developmental
A7: Antigua and Barbuda | B7: Charles III | C7: Gaston Browne | D7: Socialism | E7: S | F7: Social democracy | G7: Liberalism | H7: S/LIB | I7: Caribbean labourist social democracy (ABLP) | L7: Social-democratic Caribbean governance; market economy; tourism; moderate social policy | M7: L/C — centre-left
A8: Argentina | B8: Javier Milei | C8: Javier Milei | D8: Liberalism | E8: L+ | F8: National / populist liberalism | G8: Conservatism | H8: L+/CON | I8: Libertarian populism (Milei) | J8: Populism | L8: Radical market liberalisation; individual liberty; deregulation; reduced state; restrictive fiscal policy; socially mixed; strong Western alignment | M8: R — libertarian right, not primarily conservative
A9: Armenia | B9: Vahagn Khachaturyan | C9: Nikol Pashinyan | D9: Liberalism | E9: L | F9: Liberalism | H9: L | I9: Liberal-democratic reformism (Civil Contract) | L9: Market economy; democratic/institutional reform; secular social policy; security-focused foreign policy | M9: L/C — liberal-centrist
A10: Australia | B10: Charles III | C10: Anthony Albanese | D10: Socialism | E10: S | F10: Social democracy | G10: Liberalism | H10: S/LIB | I10: Social democracy (Labor) | J10: Ecologism | L10: Mixed economy; welfare state; multicultural migration; climate transition; alliance with US | M10: L — centre-left
A11: Austria | B11: Alexander Van der Bellen | C11: Christian Stocker | D11: Conservatism | E11: C | F11: Conservatism | G11: Socialism | H11: C/SOC | I11: Christian democracy (ÖVP-led coalition with SPÖ and NEOS) | L11: Market economy + social partnership; institutional continuity; controlled migration; pragmatic climate policy; EU/NATO-aligned security | M11: C — Christian-democratic conservative
A12: Azerbaijan | B12: Ilham Aliyev | C12: Ali Asadov | D12: Traditionalist-authoritarian | E12: T | F12: Traditionalist-authoritarian | H12: T | I12: Authoritarian state nationalism | J12: Nationalism | K12: Authoritarian rule | L12: National sovereignty; executive authority; traditional social order; hydrocarbons; restrictive migration; security-first foreign policy | M12: T — authoritarian-nationalist
A13: Bahamas | B13: Charles III | C13: Philip Davis | D13: Socialism | E13: S | F13: Social democracy | G13: Liberalism | H13: S/LIB | I13: Centre-left labourism (PLP) | L13: Social-democratic Caribbean model; tourism; moderate migration; climate/vulnerability policy | M13: L/C — centre-left
A14: Bahrain | B14: Hamad bin Isa Al Khalifa | C14: Salman bin Hamad Al Khalifa | D14: Conservatism | E14: Cm | F14: Monarchical traditionalism | G14: Religious-political ideology | H14: Cm/REL | I14: Sunni monarchical traditionalism | K14: Religion; Authoritarian rule | L14: Dynastic authority; Sunni-Islamic tradition; state-led development; controlled migration; energy diversification; security alignment | M14: T — monarchic traditionalist
A15: Bangladesh | B15: Mirza Fakhrul Islam Alamgir | C15: Tarique Rahman | D15: Conservatism | E15: C+ | F15: National / religious / populist conservatism | H15: C+ | I15: Bangladeshi-nationalist conservatism (BNP) | J15: Nationalism | K15: Religion | L15: National identity; religious/social conservatism; market economy with state role; migration/labour policy; security and sovereignty | M15: C+/N — conservative-nationalist hybrid
A16: Barbados | B16: Jeffrey Bostic | C16: Mia Mottley | D16: Socialism | E16: S | F16: Social democracy | H16: S | I16: Social democracy (BLP) | J16: Ecologism | L16: Social-democratic welfare; tourism; progressive social policy; climate resilience; multilateral foreign policy | M16: L — centre-left
A17: Belarus | B17: Alexander Lukashenko | C17: Alexander Turchin | D17: Traditionalist-authoritarian | E17: T | F17: Traditionalist-authoritarian | G17: Socialism | H17: T/SOC | I17: Authoritarian state paternalism with Soviet-nostalgic nationalism | J17: Nationalism | K17: Authoritarian rule | L17: State authority; social conservatism; state economy; restrictive migration; energy/security dependence; continuity | M17: T — authoritarian-traditionalist
A18: Belgium | B18: Philippe | C18: Bart De Wever | D18: Conservatism | E18: C+ | F18: National / religious / populist conservatism | H18: C+ | I18: Conservative Flemish nationalism (N-VA-led federal coalition) | J18: Nationalism | L18: Market economy; fiscal restraint; institutional order; stricter migration/integration; pragmatic climate/industry; NATO/EU | M18: C — national/Christian-democratic conservative
A19: Belize | B19: Charles III | C19: Johnny Briceño | D19: Socialism | E19: S | F19: Social democracy | G19: Liberalism | H19: S/LIB | I19: Centre-left (PUP) | L19: Mixed economy; social programmes; tourism; moderate migration; climate vulnerability | M19: L/C — centre-left
A20: Benin | B20: Romuald Wadagni | C20: Romuald Wadagni | D20: Liberalism | E20: L | F20: Liberalism | H20: L | I20: Technocratic market liberalism | K20: Developmentalism | L20: State capacity; economic development; market reform; order/security; infrastructure and regional security | M20: C+/T — developmental-conservative hybrid
A21: Bhutan | B21: Jigme Khesar Namgyel Wangchuck | C21: Tshering Tobgay | D21: Conservatism | E21: Cm | F21: Monarchical traditionalism | H21: Cm | I21: Buddhist monarchical traditionalism (Gross National Happiness) | J21: Ecologism | K21: Religion | L21: Monarchy and cultural continuity; regulated development; environmental stewardship; cautious social change | M21: T/C — monarchic-traditionalist
A22: Bolivia | B22: Rodrigo Paz | C22: Rodrigo Paz | D22: Liberalism | E22: L | F22: Liberalism | G22: Conservatism | H22: L/CON | I22: Centre-right market liberalism | L22: Market reform; decentralisation; security/order; moderate social conservatism; pragmatic foreign policy | M22: R — centre-right liberal
A23: Bosnia and Herzegovina | B23: Denis Bećirović / Željka Cvijanović / Željko Komšić | C23: Borjana Krišto | D23: Conservatism | E23: C+ | F23: National / religious / populist conservatism | G23: Socialism | H23: C+/SOC | I23: Consociational ethno-national conservatisms (divided presidency) | J23: Nationalism | K23: Religion | L23: Ethno-national and institutional interests; mixed economy; EU integration; migration/security; plural social positions | M23: L/C — fragmented coalition
A24: Botswana | B24: Duma Boko | C24: Duma Boko | D24: Socialism | E24: S | F24: Social democracy | G24: Liberalism | H24: S/LIB | I24: Centre-left (UDC) | L24: Social programmes; market economy; institutional democracy; mining; regional diplomacy | M24: L/C — centre-left
A25: Brazil | B25: Luiz Inácio Lula da Silva | C25: Luiz Inácio Lula da Silva | D25: Socialism | E25: S | F25: Social democracy | H25: S | I25: Democratic socialism / social democracy (PT) | J25: Ecologism | K25: Developmentalism | L25: Social welfare; developmental state; progressive social policy; environmental protection; multilateral diplomacy | M25: L — left
A26: Brunei | B26: Hassanal Bolkiah | C26: Hassanal Bolkiah | D26: Religious-political ideology | E26: RE+ | F26: Religious-national rule | G26: Conservatism | H26: RE+/CON | I26: Malay Islamic Monarchy (MIB) | J26: Nationalism | K26: Authoritarian rule | L26: Absolute monarchy; Malay-Islamic tradition; state/energy economy; restrictive social policy; controlled migration | M26: T — dynastic-religious traditionalist
A27: Bulgaria | B27: Iliana Iotova | C27: Rumen Radev | D27: Socialism | E27: S+ | F27: Left-nationalist / left-populist socialism | H27: S+ | I27: Sovereigntist left-populism (Radev) | J27: Nationalism; Populism | L27: National sovereignty; security; mixed economy; EU orientation; more restrictive migration; pragmatic energy policy | M27: C+/L — mixed centre-right/national
A28: Burkina Faso | B28: Ibrahim Traoré | C28: Jean Emmanuel Ouédraogo | D28: Socialism | E28: S+ | F28: Left-nationalist / left-populist socialism | H28: S+ | I28: Revolutionary military pan-Africanism (Sankarist) | J28: Nationalism; Populism | K28: Authoritarian rule | L28: National sovereignty; military authority; state-led development; traditional social order; restrictive external migration; anti-colonial foreign policy | M28: T — military-nationalist
A29: Burundi | B29: Évariste Ndayishimiye | C29: Nestor Ntahontuye | D29: Traditionalist-authoritarian | E29: T | F29: Traditionalist-authoritarian | H29: T | I29: Dominant-party authoritarianism (CNDD-FDD) | J29: Nationalism | K29: Religion; Authoritarian rule | L29: Executive authority; national unity; state-led development; socially conservative; security-first | M29: T/C — nationalist-authoritarian hybrid
A30: Cabo Verde | B30: José Maria Neves | C30: Francisco Carvalho | D30: Socialism | E30: S | F30: Social democracy | G30: Liberalism | H30: S/LIB | I30: Social democracy (PAICV) | L30: Democratic institutions; tourism/services; social policy; climate resilience; EU/Atlantic orientation | M30: L/C — centre-left/centrist
A31: Cambodia | B31: Norodom Sihamoni | C31: Hun Manet | D31: Traditionalist-authoritarian | E31: T | F31: Traditionalist-authoritarian | G31: Conservatism | H31: T/CON | I31: Dominant-party developmental authoritarianism (CPP) | J31: Nationalism | K31: Authoritarian rule; Developmentalism | L31: Monarchy/continuity; authority; state-led development; socially conservative; controlled migration; China/ASEAN balancing | M31: T/C — conservative-developmental
A32: Cameroon | B32: Paul Biya | C32: Joseph Ngute | D32: Traditionalist-authoritarian | E32: T | F32: Traditionalist-authoritarian | H32: T | I32: Personalist incumbency (CPDM) | K32: Authoritarian rule | L32: Executive continuity; state authority; traditional social order; resource economy; security | M32: T — authoritarian-traditionalist
A33: Canada | B33: Charles III | C33: Mark Carney | D33: Liberalism | E33: L | F33: Liberalism | H33: L | I33: Social liberalism (Liberal Party) | J33: Ecologism | L33: Market economy + welfare; multicultural migration; climate/industrial policy; Atlantic/NATO orientation | M33: L/C — liberal-centrist
A34: Central African Republic | B34: Faustin-Archange Touadéra | C34: Félix Moloua | D34: Traditionalist-authoritarian | E34: T | F34: Traditionalist-authoritarian | H34: T | I34: Personalist developmental authoritarianism | K34: Authoritarian rule | L34: Executive authority; state-led development; security; resource extraction; sovereignty | M34: T — authoritarian-developmental
A35: Chad | B35: Mahamat Déby | C35: Allamaye Halina | D35: Traditionalist-authoritarian | E35: T | F35: Traditionalist-authoritarian | H35: T | I35: Military-dynastic rule | J35: Nationalism | K35: Authoritarian rule | L35: Authority/order; security; state-led development; traditional social order; regional security | M35: T — military-nationalist
A36: Chile | B36: José Antonio Kast | C36: José Antonio Kast | D36: Conservatism | E36: C+ | F36: National / religious / populist conservatism | H36: C+ | I36: National conservatism (Kast) | J36: Nationalism | K36: Religion | L36: Traditional family/social order; law and order; private property/market economy; restrictive migration; energy pragmatism; security-oriented foreign policy | M36: C — national-conservative
A37: China | B37: Xi Jinping | C37: Li Qiang | D37: Socialism | E37: SM | F37: Marxism-Leninism | H37: SM | I37: Marxism-Leninism ('socialism with Chinese characteristics') | J37: Nationalism | K37: Authoritarian rule; Developmentalism | L37: Party authority; national continuity; state capitalism; social discipline; controlled migration; strategic autonomy | M37: T/R — communist-nationalist, not conservative in Freedenian sense
A38: Colombia | B38: Abelardo de la Espriella | C38: Abelardo de la Espriella | D38: Conservatism | E38: C+ | F38: National / religious / populist conservatism | H38: C+ | I38: National-conservative right (de la Espriella) | J38: Nationalism; Populism | L38: Security/order; market economy; traditional social values; restrictive migration; resource/energy development; strong US/security ties | M38: C+ — national-conservative
A39: Comoros | B39: Azali Assoumani | C39: Azali Assoumani | D39: Traditionalist-authoritarian | E39: T | F39: Traditionalist-authoritarian | G39: Religious-political ideology | H39: T/REL | I39: Presidential authoritarianism with Islamic social order | J39: Nationalism | K39: Religion; Authoritarian rule | L39: Executive authority; Islamic social order; state-led development; security; regional diplomacy | M39: T/C — presidential traditionalist
A40: Costa Rica | B40: Laura Fernández | C40: Laura Fernández | D40: Conservatism | E40: C+ | F40: National / religious / populist conservatism | G40: Liberalism | H40: C+/LIB | I40: Populist centre-right (Chaves continuity) | J40: Populism | L40: Security/order; market economy; fiscal reform; socially mixed; migration control; climate policy retained | M40: C+ — populist/centre-right hybrid
A41: Côte d'Ivoire | B41: Alassane Ouattara | C41: Robert Beugré Mambé | D41: Liberalism | E41: L | F41: Liberalism | H41: L | I41: Liberal developmentalism (RHDP, Houphouëtist) | K41: Developmentalism | L41: Market investment; infrastructure; state capacity; security; regional diplomacy | M41: R — developmental centre-right
A42: Croatia | B42: Zoran Milanović | C42: Andrej Plenković | D42: Conservatism | E42: C | F42: Conservatism | H42: C | I42: Christian democracy (HDZ) with nationalist partners | J42: Nationalism | L42: EU/NATO; market + social state; national identity; controlled migration; energy pragmatism; security | M42: C — Christian-democratic/national conservative
A43: Cuba | B43: Miguel Díaz-Canel | C43: Manuel Marrero Cruz | D43: Socialism | E43: SM | F43: Marxism-Leninism | H43: SM | I43: Marxism-Leninism (Communist Party of Cuba) | J43: Nationalism | K43: Authoritarian rule | L43: One-party authority; state economy; socialist social policy; controlled migration; security/sovereignty | M43: L/T — communist authoritarian
A44: Cyprus | B44: Nikos Christodoulides | C44: Nikos Christodoulides | D44: Liberalism | E44: L | F44: Liberalism | G44: Conservatism | H44: L/CON | I44: Centrist liberal conservatism | L44: Market economy; moderate social policy; EU orientation; controlled migration; energy/security in Eastern Mediterranean | M44: C/L — centrist conservative-liberal
A45: Czechia | B45: Petr Pavel | C45: Andrej Babiš | D45: Conservatism | E45: C+ | F45: National / religious / populist conservatism | H45: C+ | I45: Sovereigntist-populist right (ANO-led coalition) | J45: Nationalism; Populism | L45: Market economy with domestic spending; national sovereignty; migration restriction; climate-policy scepticism; NATO but less Ukraine activism | M45: C+ — populist-conservative hybrid
A46: Democratic Republic of the Congo | B46: Félix Tshisekedi | C46: Judith Suminwa | D46: Socialism | E46: S | F46: Social democracy | H46: S | I46: Nominal social democracy (UDPS) amid state-building | J46: Nationalism | K46: Developmentalism | L46: State capacity; resource development; social programmes; security; regional diplomacy | M46: L/C — centrist-developmental
A47: Denmark | B47: Frederik X | C47: Mette Frederiksen | D47: Socialism | E47: S | F47: Social democracy | G47: Liberalism | H47: S/LIB | I47: Social democracy with welfare-nationalist migration policy | J47: Nationalism | L47: Welfare state; restrictive migration; strong institutions; climate transition; NATO/security | M47: L/C — social-democratic with restrictive migration
A48: Djibouti | B48: Ismaïl Omar Guelleh | C48: Ismaïl Omar Guelleh | D48: Traditionalist-authoritarian | E48: T | F48: Traditionalist-authoritarian | H48: T | I48: Personalist dominant-party rule | K48: Authoritarian rule | L48: Executive authority; strategic infrastructure; state security; traditional social order; military/diplomatic balancing | M48: T — authoritarian-developmental
A49: Dominica | B49: Sylvanie Burton | C49: Roosevelt Skerrit | D49: Socialism | E49: S | F49: Social democracy | H49: S | I49: Caribbean labourist social democracy (DLP) | J49: Ecologism | L49: Public investment; social programmes; climate resilience; tourism; regional diplomacy | M49: L/C — centre-left
A50: Dominican Republic | B50: Luis Abinader | C50: Luis Abinader | D50: Liberalism | E50: L | F50: Liberalism | G50: Conservatism | H50: L/CON | I50: Centre-right liberalism (PRM) | J50: Nationalism | L50: Market economy; private investment; migration control; moderate social conservatism; tourism/energy | M50: R — moderate centre-right
A51: Ecuador | B51: Daniel Noboa | C51: Daniel Noboa | D51: Liberalism | E51: L | F51: Liberalism | G51: Conservatism | H51: L/CON | I51: Security-oriented market liberalism (Noboa) | L51: Security/order; market economy; fiscal reform; restrictive migration; energy/resource development | M51: R/C — security-oriented centre-right
A52: Egypt | B52: Abdel Fattah el-Sisi | C52: Mostafa Madbouly | D52: Traditionalist-authoritarian | E52: T | F52: Traditionalist-authoritarian | H52: T | I52: Military-backed state authoritarianism | J52: Nationalism | K52: Authoritarian rule; Developmentalism | L52: Executive authority; traditional social order; state/development projects; controlled migration; energy; regional security | M52: T — authoritarian-nationalist
A53: El Salvador | B53: Nayib Bukele | C53: Nayib Bukele | D53: Conservatism | E53: C+ | F53: National / religious / populist conservatism | H53: C+ | I53: Authoritarian populism (Bukele) | J53: Nationalism; Populism | K53: Authoritarian rule | L53: Public order/security; strong executive; pro-business with state intervention; socially conservative rhetoric; migration/security | M53: C+ — authoritarian-populist hybrid
A54: Equatorial Guinea | B54: Teodoro Obiang Nguema Mbasogo | C54: Manuel Osa Nsue Nsua | D54: Traditionalist-authoritarian | E54: T | F54: Traditionalist-authoritarian | H54: T | I54: Personalist-dynastic rule | K54: Authoritarian rule | L54: Executive continuity; oil/state economy; social traditionalism; controlled migration; security | M54: T — authoritarian-traditionalist
A55: Eritrea | B55: Isaias Afwerki | C55: Isaias Afwerki | D55: Traditionalist-authoritarian | E55: T | F55: Traditionalist-authoritarian | G55: Socialism | H55: T/SOC | I55: Revolutionary militarised single-party rule (PFDJ) | J55: Nationalism | K55: Authoritarian rule | L55: National sovereignty; state control; social discipline; restricted migration; militarised security | M55: T — authoritarian-nationalist
A56: Estonia | B56: Alar Karis | C56: Kristen Michal | D56: Liberalism | E56: L | F56: Liberalism | G56: Conservatism | H56: L/CON | I56: Market liberalism (Reform Party) | L56: Market economy; national security; restrictive migration/integration; digital state; strong NATO/EU orientation | M56: C/L — liberal-conservative
A57: Eswatini | B57: Mswati III | C57: Russell Dlamini | D57: Conservatism | E57: Cm | F57: Monarchical traditionalism | H57: Cm | I57: Absolute monarchical traditionalism | K57: Authoritarian rule | L57: Monarchical authority; customary tradition; state-led development; socially conservative; controlled migration | M57: T — monarchic traditionalist
A58: Ethiopia | B58: Taye Atske Selassie | C58: Abiy Ahmed | D58: Traditionalist-authoritarian | E58: T | F58: Traditionalist-authoritarian | G58: Liberalism | H58: T/LIB | I58: Developmental-state authoritarianism (Prosperity Party) | J58: Nationalism | K58: Authoritarian rule; Developmentalism | L58: State capacity; developmentalism; mixed economy; traditional social order; security; regional diplomacy | M58: C+/T — developmental-authoritarian hybrid
A59: Federated States of Micronesia | B59: Wesley Simina | C59: Wesley Simina | D59: Liberalism | E59: L | F59: Liberalism | H59: L | I59: Non-partisan consensus centrism | J59: Ecologism | L59: Climate adaptation; public services; US security compact; migration/mobility | M59: L/C — centrist
A60: Fiji | B60: Naiqama Lalabalavu | C60: Sitiveni Rabuka | D60: Conservatism | E60: C | F60: Conservatism | G60: Liberalism | H60: C/LIB | I60: Indigenous-communitarian conservatism (People's Alliance) | L60: Market/tourism economy; customary institutions; moderate social conservatism; climate vulnerability; regional security | M60: C/L — conservative-liberal hybrid
A61: Finland | B61: Alexander Stubb | C61: Petteri Orpo | D61: Conservatism | E61: C | F61: Conservatism | H61: C | I61: Liberal conservatism (Kokoomus) in coalition with the Finns Party | J61: Nationalism | L61: Market economy; fiscal discipline; institutional continuity; restrictive migration; nuclear/climate pragmatism; strong NATO | M61: C — liberal/Christian-democratic conservative
A62: France | B62: Emmanuel Macron | C62: Sébastien Lecornu | D62: Liberalism | E62: L | F62: Liberalism | H62: L | I62: Liberal centrism (Macronism) | L62: State capacity; market reform; secular republicanism; controlled migration; nuclear/energy transition; European strategic autonomy | M62: L/C — liberal-centrist, not primarily conservative
A63: Gabon | B63: Brice Oligui Nguema | C63: Brice Oligui Nguema | D63: Traditionalist-authoritarian | E63: T | F63: Traditionalist-authoritarian | H63: T | I63: Military-developmental rule (post-transition) | J63: Nationalism | K63: Authoritarian rule; Developmentalism | L63: Military authority; national resources; state-led development; social traditionalism; security | M63: T — military-developmental
A64: Gambia | B64: Adama Barrow | C64: Adama Barrow | D64: Liberalism | E64: L | F64: Liberalism | H64: L | I64: Liberal-democratic centrism | L64: Market/tourism; democratic institutions; moderate social policy; migration and regional diplomacy | M64: L/C — centrist
A65: Georgia | B65: Mikheil Kavelashvili | C65: Irakli Kobakhidze | D65: Conservatism | E65: C+ | F65: National / religious / populist conservatism | H65: C+ | I65: National conservatism (Georgian Dream) | J65: Nationalism; Populism | K65: Religion; Authoritarian rule | L65: National sovereignty; Orthodox cultural tradition; authority/order; restrictive NGO/foreign influence policy; migration/security; cautious EU orientation | M65: C+ — national/traditionalist
A66: Germany | B66: Frank-Walter Steinmeier | C66: Friedrich Merz | D66: Conservatism | E66: C | F66: Conservatism | G66: Socialism | H66: C/SOC | I66: Christian democracy (CDU/CSU–SPD coalition) | L66: Social market; fiscal discipline; property/private enterprise; controlled migration; industrial climate transition; strong EU/NATO | M66: C — Christian-democratic conservative
A67: Ghana | B67: John Mahama | C67: John Mahama | D67: Socialism | E67: S | F67: Social democracy | G67: Liberalism | H67: S/LIB | I67: Social democracy (NDC) | K67: Developmentalism | L67: Social/developmental state; market economy; democratic institutions; regional diplomacy | M67: L/C — centre-left
A68: Greece | B68: Konstantinos Tasoulas | C68: Kyriakos Mitsotakis | D68: Conservatism | E68: C | F68: Conservatism | G68: Liberalism | H68: C/LIB | I68: Liberal conservatism (New Democracy) | L68: Market reform; institutional continuity; controlled migration; family/social conservatism; renewables + energy security; NATO/EU | M68: C — liberal-conservative
A69: Grenada | B69: Charles III | C69: Dickon Mitchell | D69: Socialism | E69: S | F69: Social democracy | H69: S | I69: Social democracy (NDC) | J69: Ecologism | L69: Social programmes; tourism; climate resilience; regional diplomacy | M69: L/C — centre-left
A70: Guatemala | B70: Bernardo Arévalo | C70: Bernardo Arévalo | D70: Socialism | E70: S | F70: Social democracy | G70: Liberalism | H70: S/LIB | I70: Social-democratic anti-corruption reformism (Arévalo) | L70: Anti-corruption/institutional reform; market economy; moderate social policy; migration/development | M70: L/C — liberal-centrist
A71: Guinea | B71: Mamady Doumbouya | C71: Bah Oury | D71: Traditionalist-authoritarian | E71: T | F71: Traditionalist-authoritarian | H71: T | I71: Military rule (Doumbouya) | J71: Nationalism | K71: Authoritarian rule | L71: Military authority; national resources; state capacity; traditional social order; security | M71: T — military-nationalist
A72: Guinea-Bissau | B72: Horta Inta-A Na Man | C72: Ilídio Vieira Té | D72: Traditionalist-authoritarian | E72: T | F72: Traditionalist-authoritarian | H72: T | I72: Military transitional rule | K72: Authoritarian rule | L72: Order/security; state continuity; resource/tactical governance | M72: T — military/transitional
A73: Guyana | B73: Irfaan Ali | C73: Irfaan Ali | D73: Socialism | E73: S | F73: Social democracy | G73: Liberalism | H73: S/LIB | I73: Developmental centre-left (PPP/C) | K73: Developmentalism | L73: Resource-led development; infrastructure; market economy; social programmes; security/foreign investment | M73: L/C — developmental-centrist
A74: Haiti | B74: Vacant | C74: Alix Didier Fils-Aimé | D74: Liberalism | E74: L | F74: Liberalism | H74: L | I74: Transitional technocratic government | L74: Security/order; institutional rebuilding; humanitarian governance; migration/displacement | M74: T/L — transitional security government
A75: Honduras | B75: Nasry Asfura | C75: Nasry Asfura | D75: Conservatism | E75: C | F75: Conservatism | G75: Liberalism | H75: C/LIB | I75: Conservatism (National Party) | K75: Religion | L75: Security/order; private investment; traditional social values; restrictive migration; market economy | M75: C — national-conservative
A76: Hungary | B76: András Baka | C76: Péter Magyar | D76: Conservatism | E76: C | F76: Conservatism | G76: Liberalism | H76: C/LIB | I76: Centre-right conservatism (Tisza, post-Orbán) | L76: EU-oriented centre-right; market economy; institutional repair; controlled migration; moderate social conservatism; security | M76: C — centre-right conservative, post-Orbán
A77: Iceland | B77: Halla Tómasdóttir | C77: Kristrún Frostadóttir | D77: Socialism | E77: S | F77: Social democracy | G77: Liberalism | H77: S/LIB | I77: Social democracy (Alliance-led coalition) | J77: Ecologism; Feminism | L77: Welfare state; market economy; climate/energy; moderate migration; Nordic institutions | M77: L/C — social-democratic
A78: India | B78: Droupadi Murmu | C78: Narendra Modi | D78: Conservatism | E78: C+ | F78: National / religious / populist conservatism | H78: C+ | I78: Hindu-nationalist conservatism (Hindutva, BJP) | J78: Nationalism; Populism | K78: Religion | L78: Hindu cultural/national identity; strong executive; mixed market/state development; restrictive citizenship/migration; energy pragmatism; strategic autonomy | M78: C+ — national-cultural conservative
A79: Indonesia | B79: Prabowo Subianto | C79: Prabowo Subianto | D79: Conservatism | E79: C+ | F79: National / religious / populist conservatism | H79: C+ | I79: Developmental-nationalist conservatism (Prabowo, Pancasila) | J79: Nationalism; Populism | K79: Developmentalism | L79: National unity; authority; state-led industrial policy; social/family conservatism; migration controlled; resource/energy development; strategic autonomy | M79: C+ — nationalist-developmental
A80: Iran | B80: Mojtaba Khamenei | C80: Masoud Pezeshkian | D80: Religious-political ideology | E80: RE | F80: Theocracy | H80: RE | I80: Islamist theocracy (velayat-e faqih) | J80: Nationalism | K80: Authoritarian rule | L80: Islamic order; clerical authority; state-led economy; restrictive social policy; controlled migration; security/sovereignty | M80: T — religious-authoritarian
A81: Iraq | B81: Nizar Amidi | C81: Ali al-Zaidi | D81: Religious-political ideology | E81: RE+ | F81: Religious-national rule | H81: RE+ | I81: Shia Islamist coalition politics in a consociational order | J81: Nationalism | L81: Religious/social tradition; authority; state/resources; security; migration/displacement; regional balancing | M81: C+/T — religious-national coalition
A82: Ireland | B82: Catherine Connolly | C82: Micheál Martin | D82: Liberalism | E82: L | F82: Liberalism | G82: Conservatism | H82: L/CON | I82: Centrist liberalism (Fianna Fáil–Fine Gael) | L82: Market economy + welfare; relatively liberal social policy; migration/integration; climate transition; EU/Atlantic orientation | M82: L/C — centrist
A83: Israel | B83: Isaac Herzog | C83: Benjamin Netanyahu | D83: Conservatism | E83: C+ | F83: National / religious / populist conservatism | H83: C+ | I83: National conservatism / religious Zionism (Likud-led coalition) | J83: Nationalism; Populism | K83: Religion | L83: Jewish national identity; security/order; market economy; socially conservative coalition; restrictive migration; defence-first foreign policy | M83: C+ — national-conservative
A84: Italy | B84: Sergio Mattarella | C84: Giorgia Meloni | D84: Conservatism | E84: C+ | F84: National / religious / populist conservatism | H84: C+ | I84: National conservatism (Fratelli d'Italia) | J84: Nationalism | L84: Traditional family/cultural identity; market + strategic state; restrictive migration; energy pragmatism; strong NATO/EU with sovereignty emphasis | M84: C+ — national-conservative
A85: Jamaica | B85: Charles III | C85: Andrew Holness | D85: Conservatism | E85: C | F85: Conservatism | G85: Liberalism | H85: C/LIB | I85: Centre-right conservatism (JLP) | L85: Private enterprise; law/order; moderate social conservatism; controlled migration; tourism/energy | M85: C/L — centre-right conservative
A86: Japan | B86: Naruhito | C86: Sanae Takaichi | D86: Conservatism | E86: C+ | F86: National / religious / populist conservatism | H86: C+ | I86: National conservatism (LDP, Takaichi) | J86: Nationalism | L86: Traditional institutions/family; national identity; market economy + fiscal stimulus; stronger defence; energy/nuclear pragmatism | M86: C+ — national-conservative
A87: Jordan | B87: Abdullah II | C87: Jafar Hassan | D87: Conservatism | E87: Cm | F87: Monarchical traditionalism | G87: Religious-political ideology | H87: Cm/REL | I87: Hashemite monarchical traditionalism | K87: Religion | L87: Monarchical authority; Islamic/tribal tradition; state-led economy; controlled migration/refugees; security diplomacy | M87: T — monarchic traditionalist
A88: Kazakhstan | B88: Kassym-Jomart Tokayev | C88: Oljas Bektenov | D88: Traditionalist-authoritarian | E88: T | F88: Traditionalist-authoritarian | H88: T | I88: Developmental authoritarianism | J88: Nationalism | K88: Authoritarian rule; Developmentalism | L88: Executive order; national identity; state/resource economy; controlled migration; energy development; multi-vector diplomacy | M88: T — authoritarian-developmental
A89: Kenya | B89: William Ruto | C89: William Ruto | D89: Conservatism | E89: C+ | F89: National / religious / populist conservatism | G89: Liberalism | H89: C+/LIB | I89: Religious-social conservatism with market liberalism (Ruto) | J89: Populism | K89: Religion | L89: Religious/family values; market reform; security/order; migration management; development/energy; regional diplomacy | M89: C+ — social/religious conservative + market-oriented
A90: Kiribati | B90: Taneti Maamau | C90: Taneti Maamau | D90: Liberalism | E90: L | F90: Liberalism | H90: L | I90: Small-state communitarian centrism | J90: Ecologism | L90: Community/tradition; public development; climate adaptation; migration/mobility; regional diplomacy | M90: L/C — developmental-centrist
A91: Kuwait | B91: Mishal Al-Ahmad Al-Sabah | C91: Ahmad Al-Abdullah Al-Sabah | D91: Conservatism | E91: Cm | F91: Monarchical traditionalism | G91: Religious-political ideology | H91: Cm/REL | I91: Monarchical traditionalism (parliament suspended) | K91: Religion; Authoritarian rule | L91: Dynastic authority; Islamic tradition; oil/state economy; controlled migration; energy; Gulf security | M91: T — monarchic traditionalist
A92: Kyrgyzstan | B92: Sadyr Japarov | C92: Sadyr Japarov | D92: Traditionalist-authoritarian | E92: T | F92: Traditionalist-authoritarian | G92: Conservatism | H92: T/CON | I92: Authoritarian populism (Japarov) | J92: Nationalism; Populism | K92: Authoritarian rule | L92: Executive authority; national identity; state intervention; social conservatism; migration/security; regional balancing | M92: C+/T — nationalist-authoritarian hybrid
A93: Laos | B93: Thongloun Sisoulith | C93: Sonexay Siphandone | D93: Socialism | E93: SM | F93: Marxism-Leninism | H93: SM | I93: Marxism-Leninism (Lao People's Revolutionary Party) | K93: Authoritarian rule | L93: Party authority; state economy; social discipline; controlled migration; hydropower/resources; regional balancing | M93: T/L — communist-authoritarian
A94: Latvia | B94: Edgars Rinkēvičs | C94: Andris Kulbergs | D94: Liberalism | E94: L | F94: Liberalism | G94: Conservatism | H94: L/CON | I94: Centre-right liberalism | L94: Market economy; national security; controlled migration; energy diversification; NATO/EU | M94: R — centre-right liberal
A95: Lebanon | B95: Joseph Aoun | C95: Nawaf Salam | D95: Liberalism | E95: L | F95: Liberalism | H95: L | I95: Reformist technocratic liberalism within confessional consociationalism | K95: Religion | L95: Sectarian balance; market/private economy; institutional reconstruction; refugee/migration pressures; regional security | M95: L/C — institutional/coalitional
A96: Lesotho | B96: Letsie III | C96: Sam Matekane | D96: Liberalism | E96: L | F96: Liberalism | H96: L | I96: Market-developmental centre-right (RFP) | K96: Developmentalism | L96: Market investment; customary institutions; social programmes; migration/labour; regional diplomacy | M96: R — centre-right developmental
A97: Liberia | B97: Joseph Boakai | C97: Joseph Boakai | D97: Liberalism | E97: L | F97: Liberalism | H97: L | I97: Liberal-democratic centrism (Unity Party) | L97: Institutional reform; market economy; development; moderate social policy; regional diplomacy | M97: L/C — centrist
A98: Libya | B98: Mohamed al-Menfi | C98: Abdul Hamid Dbeibeh | D98: Traditionalist-authoritarian | E98: T | F98: Traditionalist-authoritarian | G98: Liberalism | H98: T/LIB | I98: Fragmented state-building (rival authorities) | L98: State reconstruction; competing authorities; market/resource economy; migration/security; regional balancing | M98: L/C — fragmented transitional
A99: Liechtenstein | B99: Hans-Adam II | C99: Brigitte Haas | D99: Conservatism | E99: C | F99: Conservatism | G99: Liberalism | H99: C/LIB | I99: Liberal conservatism under constitutional monarchy | L99: Property/private enterprise; constitutional monarchy; low-tax economy; institutional continuity; European cooperation | M99: C — liberal-conservative
A100: Lithuania | B100: Gitanas Nausėda | C100: Mindaugas Sinkevičius | D100: Socialism | E100: S | F100: Social democracy | H100: S | I100: Social democracy (LSDP-led coalition with a national-populist partner) | J100: Nationalism | L100: Market economy; national security; migration control/integration; energy independence; NATO/EU | M100: R — centre-right security-oriented
...

Sheet Summary
A1: Family | B1: States | C1: Share of states
A2: Liberalism | B2: =COUNTIF('195 States'!$D$2:$D$196,A2) | C2: =B2/$B$8
A3: Conservatism | B3: =COUNTIF('195 States'!$D$2:$D$196,A3) | C3: =B3/$B$8
A4: Socialism | B4: =COUNTIF('195 States'!$D$2:$D$196,A4) | C4: =B4/$B$8
A5: Religious-political ideology | B5: =COUNTIF('195 States'!$D$2:$D$196,A5) | C5: =B5/$B$8
A6: Traditionalist-authoritarian | B6: =COUNTIF('195 States'!$D$2:$D$196,A6) | C6: =B6/$B$8
A7: Total | B7: =SUM(B2:B6) | C7: =SUM(C2:C6)
A8: States in dataset | B8: =COUNTA('195 States'!$A$2:$A$196)
A10: Variant code | B10: Variant | C10: Family | D10: States | E10: Definition
A11: L | B11: Liberalism | C11: Liberalism | D11: =COUNTIF('195 States'!$E$2:$E$196,A11) | E11: Clear liberal morphology: social, market or centrist liberalism.
A12: L+ | B12: National / populist liberalism | C12: Liberalism | D12: =COUNTIF('195 States'!$E$2:$E$196,A12) | E12: Liberal core combined strongly with nationalism or populism.
A13: C | B13: Conservatism | C13: Conservatism | D13: =COUNTIF('195 States'!$E$2:$E$196,A13) | E13: Clear conservative morphology: Christian-democratic, liberal-conservative or customary conservatism.
A14: C+ | B14: National / religious / populist conservatism | C14: Conservatism | D14: =COUNTIF('195 States'!$E$2:$E$196,A14) | E14: Conservative core combined strongly with nationalism, populism, religion or authoritarianism.
A15: Cm | B15: Monarchical traditionalism | C15: Conservatism | D15: =COUNTIF('195 States'!$E$2:$E$196,A15) | E15: A ruling monarchy manages change from above to preserve a dynastic and often religious order.
A16: S | B16: Social democracy | C16: Socialism | D16: =COUNTIF('195 States'!$E$2:$E$196,A16) | E16: Social democracy or democratic socialism within a competitive democracy.
A17: S+ | B17: Left-nationalist / left-populist socialism | C17: Socialism | D17: =COUNTIF('195 States'!$E$2:$E$196,A17) | E17: Socialist core combined strongly with nationalism, populism or authoritarianism.
A18: SM | B18: Marxism-Leninism | C18: Socialism | D18: =COUNTIF('195 States'!$E$2:$E$196,A18) | E18: Communist party-state; the party's doctrine organises state and economy.
A19: RE | B19: Theocracy | C19: Religious-political ideology | D19: =COUNTIF('195 States'!$E$2:$E$196,A19) | E19: Religious doctrine and clerical authority define the state.
A20: RE+ | B20: Religious-national rule | C20: Religious-political ideology | D20: =COUNTIF('195 States'!$E$2:$E$196,A20) | E20: Religious legitimacy fused with dynastic or national authority.
A21: T | B21: Traditionalist-authoritarian | C21: Traditionalist-authoritarian | D21: =COUNTIF('195 States'!$E$2:$E$196,A21) | E21: Order, hierarchy and continuity without a sustained macro-ideology (military, personalist or dominant-party rule).
A22: Total | D22: =SUM(D11:D21)
A24: Component | B24: Type | D24: States
A25: Nationalism | B25: Thin-centred ideology | D25: =COUNTIF('195 States'!$J$2:$J$196,"*"&A25&"*")
A26: Populism | B26: Thin-centred ideology | D26: =COUNTIF('195 States'!$J$2:$J$196,"*"&A26&"*")
A27: Ecologism | B27: Thin-centred ideology | D27: =COUNTIF('195 States'!$J$2:$J$196,"*"&A27&"*")
A28: Feminism | B28: Thin-centred ideology | D28: =COUNTIF('195 States'!$J$2:$J$196,"*"&A28&"*")
A29: Religion | B29: Adjacent concept | D29: =COUNTIF('195 States'!$K$2:$K$196,"*"&A29&"*")
A30: Developmentalism | B30: Adjacent concept | D30: =COUNTIF('195 States'!$K$2:$K$196,"*"&A30&"*")
A31: Authoritarian rule | B31: Regime context (not an ideology) | D31: =COUNTIF('195 States'!$K$2:$K$196,"*"&A31&"*")

Sheet Methodology
A1: Field | B1: Definition / note
A2: Snapshot date | B2: 2026-10-03 (leaders as in the corrected conservatism dataset of the same date)
A3: Coverage | B3: 195 states: 193 UN members + Palestine + Vatican City. Country names follow UN short names.
A4: Leader source | B4: Wikipedia list of current heads of state and government (retrieved 2026-10-03), cross-checked against news reports. Unchanged from the source dataset.
A5: Framework | B5: Michael Freeden's morphological approach: an ideology is a configuration of core, adjacent and peripheral concepts, each 'decontested' (given one settled meaning). Families are identified by their core concepts, not by a left-right position or a checklist of policies. Each family appears in several decontested variants.
A6: Unit coded | B6: The governing ideology of the executive that actually directs policy (normally the head of government, or the head of state where executive power sits there). A ceremonial head of state does not determine the code.
A7: Ideological family | B7: The macro-ideology whose core concepts organise the government's programme: Liberalism, Conservatism, Socialism, plus Religious-political ideology and a residual Traditionalist-authoritarian category. Nationalism is never coded as the family: in Freeden's account it is thin-centred and needs a host, so it is recorded as a component (and signalled by "+" variants).
A8: Liberalism | B8: Core concepts (Freeden): liberty, rationality, individuality, progress, sociability, the general interest, and limited, accountable power.
A9: Conservatism | B9: Core concepts (Freeden): change must be controlled so that it appears natural and organic; social order has extra-human origins (history, God, nature, the market or monarchy) and is independent of human will.
A10: Socialism | B10: Core concepts (Freeden): the constitutive nature of the group, equality, human welfare as the goal of politics, human activity/praxis, and history as the arena of change.
A11: Religious-political ideology | B11: Political order is derived from religious doctrine and religious authority. Not one of Freeden's three macro-ideologies; included because his morphological method treats such belief systems as ideologies with their own core concepts (divine sovereignty, sacred law, clerical or dynastic-religious authority).
A12: Traditionalist-authoritarian | B12: Residual category, not a Freeden family: hierarchy, order, continuity and state authority dominate, but no liberal, conservative or socialist programme is sustained at the core. Typical of military, personalist and dominant-party regimes. Calling these conservative would overstate the presence of conservative morphology; nationalism usually appears as a component.
... A30: Caveat | B30: Codes are interpretive judgements for teaching and discussion, not measurements. Coalitions, caretaker and transitional governments are coded by their dominant governing morphology. The policy column is descriptive and unchanged from the source dataset.

Sheet Sources
A1: Use | B1: Source | C1: URL
A2: Current leaders | B2: UN Protocol & Liaison Service | C2: https://www.un.org/dgacm/en/content/protocol/hshgnfa
A3: Current leaders cross-check | B3: CIA World Leaders | C3: https://www.cia.gov/resources/world-leaders/
A4: Current heads list used for 2026 snapshot | B4: Wikipedia – List of current heads of state and government | C4: https://en.wikipedia.org/wiki/List_of_current_heads_of_state_and_government
A5: Freeden framework | B5: Stanford Encyclopedia of Philosophy – Conservatism | C5: https://seop.illc.uva.nl/entries/conservatism/
A6: Freeden framework | B6: Freeden, M. (1996) Ideologies and Political Theory: A Conceptual Approach. Oxford: Clarendon Press.
A7: Thin-centred nationalism | B7: Freeden, M. (1998) "Is Nationalism a Distinct Ideology?" Political Studies 46(4): 748-765. | C7: https://doi.org/10.1111/1467-9248.00165
A8: Freeden framework (introductory) | B8: Freeden, M. (2003) Ideology: A Very Short Introduction. Oxford: Oxford University Press.
A9: Families and variants | B9: Freeden, M., Sargent, L.T. and Stears, M. (eds) (2013) The Oxford Handbook of Political Ideologies. Oxford: Oxford University Press.
A10: Thin-centred populism | B10: Mudde, C. (2004) "The Populist Zeitgeist." Government and Opposition 39(4): 541-563. | C10: https://doi.org/10.1111/j.1477-7053.2004.00135.x

Sheet Change log
A1: Type | B1: Country | C1: Field | D1: Old value | E1: New value | F1: Reason
A2: Recoding | B2: All 195 states | C2: Classification | D2: Five families with nationalism as a possible primary family (LIB, CON, SOC, NAT, REL) | E2: Variants within each family (L, L+; C, C+, Cm; S, S+, SM; RE, RE+) plus residual T; nationalism only as a component | F2: Nationalism is thin-centred (Freeden 1998) and is not treated as a host ideology; variants show the range of decontested forms within each family, as C and C+ did in the conservatism scheme
A3: Recoding | B3: Algeria | C3: Classification | D3: NAT/SOC | E3: S+ | F3: Former NAT-primary state reassigned to the family whose core concepts it draws on, or to the residual T category
A4: Recoding | B4: Angola | C4: Classification | D4: NAT/SOC | E4: T/SOC | F4: Former NAT-primary state reassigned to the family whose core concepts it draws on, or to the residual T category
A5: Recoding | B5: Azerbaijan | C5: Classification | D5: NAT | E5: T | F5: Former NAT-primary state reassigned to the family whose core concepts it draws on, or to the residual T category
A6: Recoding | B6: Bangladesh | C6: Classification | D6: NAT/CON | E6: C+ | F6: Former NAT-primary state reassigned to the family whose core concepts it draws on, or to the residual T category
A7: Recoding | B7: Belarus | C7: Classification | D7: NAT/CON | E7: T/SOC | F7: Former NAT-primary state reassigned to the family whose core concepts it draws on, or to the residual T category
A8: Recoding | B8: Bosnia and Herzegovina | C8: Classification | D8: NAT/LIB | E8: C+/SOC | F8: Former NAT-primary state reassigned to the family whose core concepts it draws on, or to the residual T category
A9: Recoding | B9: Bulgaria | C9: Classification | D9: NAT/SOC | E9: S+ | F9: Former NAT-primary state reassigned to the family whose core concepts it draws on, or to the residual T category
A10: Recoding | B10: Burkina Faso | C10: Classification | D10: NAT/SOC | E10: S+ | F10: Former NAT-primary state reassigned to the family whose core concepts it draws on, or to the residual T category
A11: Recoding | B11: Burundi | C11: Classification | D11: NAT | E11: T | F11: Former NAT-primary state reassigned to the family whose core concepts it draws on, or to the residual T category
A12: Recoding | B12: Cambodia | C12: Classification | D12: NAT/CON | E12: T/CON | F12: Former NAT-primary state reassigned to the family whose core concepts it draws on, or to the residual T category
... A111: Naming | B111: Turkey | C111: Country | D111: Turkey | E111: Türkiye | F111: Use UN official short name
